README.rst
setup.py
OttawaCityJobs.egg-info/PKG-INFO
OttawaCityJobs.egg-info/SOURCES.txt
OttawaCityJobs.egg-info/dependency_links.txt
OttawaCityJobs.egg-info/pbr.json
OttawaCityJobs.egg-info/requires.txt
OttawaCityJobs.egg-info/top_level.txt
ottawacityjobs/__init__.py