Metadata-Version: 1.1
Name: OttawaCityJobs
Version: 0.1.3
Summary: Yet another ottawa city jobs scrapper
Home-page: https://github.com/guinslym/ottawajobs
Author: Guinslym
Author-email: guinslym@gmail.com
License: GNU GPLv2
Keywords: json scrapper jobs city Ottawa
Platform: UNKNOWN
Classifier: Development Status :: 5 - Production/Stable
Classifier: Intended Audience :: Developers
Classifier: License :: OSI Approved :: GNU General Public License v3 or later (GPLv3+)
Classifier: Programming Language :: Python :: 2
Classifier: Programming Language :: Python :: 2.6
Classifier: Programming Language :: Python :: 2.7
Classifier: Programming Language :: Python :: 3
Classifier: Programming Language :: Python :: 3.2
Classifier: Programming Language :: Python :: 3.3
Classifier: Programming Language :: Python :: 3.4
Classifier: Topic :: Internet :: WWW/HTTP :: Indexing/Search
